{
  "$schema": "https://mintlify.com/docs.json",
  "theme": "mint",
  "name": "ip.world",
  "colors": {
    "primary": "#AD74FE",
    "light": "#FE74EC",
    "dark": "#7C3AED"
  },
  "favicon": "/favicon.svg",
  "navigation": {
    "tabs": [
      {
        "tab": "User Guides",
        "groups": [
          {
            "group": "Start here",
            "pages": [
              "index",
              "user-guides/what-is-ipworld",
              "user-guides/ips-and-tokens",
              "user-guides/getting-started",
              "user-guides/app-tour"
            ]
          },
          {
            "group": "Account & profile",
            "pages": [
              "user-guides/account/login-and-wallets",
              "user-guides/account/settings-and-profile",
              "user-guides/account/connecting-socials"
            ]
          },
          {
            "group": "Explore",
            "pages": [
              "user-guides/explore/navigating-ips",
              "user-guides/explore/navigating-tokens",
              "user-guides/explore/search-and-filters"
            ]
          },
          {
            "group": "Create",
            "pages": [
              "user-guides/create/creating-an-ip",
              "user-guides/create/creating-a-token",
              "user-guides/create/metadata-socials-and-antisnipe"
            ]
          },
          {
            "group": "Verification & claiming",
            "pages": [
              "user-guides/verification/verification-overview",
              "user-guides/verification/creator-vs-community-ips",
              "user-guides/verification/getting-verified",
              "user-guides/verification/claiming-a-creator-ip",
              "user-guides/verification/ip-token-license-itl"
            ]
          },
          {
            "group": "Manage",
            "pages": [
              "user-guides/manage/creator-ip-management",
              "user-guides/manage/community-ip-governance",
              "user-guides/manage/endorsements"
            ]
          },
          {
            "group": "Growth",
            "pages": [
              "user-guides/growth/referrals"
            ]
          },
          {
            "group": "Reference",
            "pages": [
              "user-guides/reference/faq",
              "user-guides/reference/glossary"
            ]
          }
        ]
      },
      {
        "tab": "Dev Docs",
        "groups": [
          {
            "group": "Overview",
            "pages": [
              "dev/index"
            ]
          },
          {
            "group": "Platform",
            "pages": [
              "dev/authentication",
              "dev/api",
              "dev/webhooks"
            ]
          }
        ]
      }
    ],
    "global": {
      "anchors": [
        {
          "anchor": "Open App",
          "href": "https://ip.world",
          "icon": "globe"
        },
        {
          "anchor": "Discord",
          "href": "http://discord.gg/ipworld",
          "icon": "discord"
        }
      ]
    }
  },
  "logo": {
    "light": "/logo/light.svg",
    "dark": "/logo/dark.svg"
  },
  "navbar": {
    "links": [
      {
        "label": "X",
        "href": "https://x.com/ipdotworld"
      },
      {
        "label": "Discord",
        "href": "http://discord.gg/ipworld"
      }
    ],
    "primary": {
      "type": "button",
      "label": "App",
      "href": "https://ip.world"
    }
  },
  "contextual": {
    "options": [
     "copy",
     "view",
     "cursor",
     "vscode"
   ]
  },
  "footer": {
    "socials": {
      "x": "https://x.com/ipdowtworld",
      "discord": "http://discord.gg/ipworld",
      "github": "https://github.com/ipdotworld"
    }
  }
}
